{
  "title": "Demo - ITER",
  "author": "Curt Henrichs",
  "version": "0.0.1",
  "frame_id": "base_link",
  "environment": [],
  "task": [
    {
      "name": "grasp",
      "effort": 0.4
    },
    {
        "name": "wait",
        "condition": "button"
    },
    {
      "name": "publish_string_from_file",
      "topic": "/ur_driver/URScript",
      "filepath": "../Workspaces/iter_ws/src/ITER/iter_app/urscript/reciprocal_p1_1.script"
    },
    {
      "name": "wait",
      "condition": "time",
      "value": 15
    },
    {
        "name": "wait",
        "condition": "button"
    }
  ]
}
